{
    "configurations": [
        {
            "name": "ESP32-S3",
            "includePath": [
                "${workspaceFolder}/**",
                "${workspaceFolder}/managed_components/**",
                "${HOME}/.espressif/tools/xtensa-esp32s3-elf/**",
                "${HOME}/esp/esp-idf/components/freertos/FreeRTOS-Kernel/include/**",
                "${HOME}/esp/esp-idf/components/**"
            ],
            "defines": [],
            "compilerPath": "${config:idf.toolsPath}/tools/xtensa-esp32s3-elf/esp-12.2.0_20230208/xtensa-esp32s3-elf/bin/xtensa-esp32s3-elf-gcc",
            "cStandard": "c17",
            "cppStandard": "gnu++17",
            "intelliSenseMode": "${default}",
            "configurationProvider": "None"
        }
    ],
    "version": 4
}
